thoth_dbmanager/ThothDbManager.py
thoth_dbmanager/__init__.py
thoth_dbmanager/documents.py
thoth_dbmanager/dynamic_imports.py
thoth_dbmanager/adapters/__init__.py
thoth_dbmanager/adapters/informix_ssh.py
thoth_dbmanager/adapters/mariadb.py
thoth_dbmanager/adapters/postgresql.py
thoth_dbmanager/adapters/sqlite.py
thoth_dbmanager/adapters/sqlserver.py
thoth_dbmanager/core/__init__.py
thoth_dbmanager/core/factory.py
thoth_dbmanager/core/interfaces.py
thoth_dbmanager/core/registry.py
thoth_dbmanager/helpers/__init__.py
thoth_dbmanager/helpers/multi_db_generator.py
thoth_dbmanager/helpers/preprocess_values.py
thoth_dbmanager/helpers/schema.py
thoth_dbmanager/helpers/search.py
thoth_dbmanager/helpers/ssh_tunnel.py
thoth_dbmanager/lsh/__init__.py
thoth_dbmanager/lsh/core.py
thoth_dbmanager/lsh/factory.py
thoth_dbmanager/lsh/manager.py
thoth_dbmanager/lsh/storage.py
thoth_dbmanager/plugins/__init__.py
thoth_dbmanager/plugins/informix.py
thoth_dbmanager/plugins/mariadb.py
thoth_dbmanager/plugins/postgresql.py
thoth_dbmanager/plugins/sqlite.py
thoth_dbmanager/plugins/sqlserver.py
thoth_dbmanager-0.7.4.dist-info/licenses/LICENSE.md
thoth_dbmanager-0.7.4.dist-info/METADATA
thoth_dbmanager-0.7.4.dist-info/WHEEL
thoth_dbmanager-0.7.4.dist-info/top_level.txt
thoth_dbmanager-0.7.4.dist-info/RECORD
