Metadata-Version: 2.4
Name: thoth_dbmanager
Version: 0.7.4
Summary: A Python library for managing SQL databases with support for multiple database types, LSH-based similarity search, and a modern plugin architecture.
Author-email: Marco Pancotti <mp@tylconsulting.it>
Project-URL: Homepage, https://github.com/mptyl/thoth_dbmanager
Project-URL: Bug Tracker, https://github.com/mptyl/thoth_dbmanager/issues
Project-URL: Documentation, https://github.com/mptyl/thoth_dbmanager#readme
Project-URL: Source Code, https://github.com/mptyl/thoth_dbmanager
Keywords: database,sql,lsh,similarity-search,orm
Classifier: Programming Language :: Python :: 3
Classifier: Programming Language :: Python :: 3.9
Classifier: Programming Language :: Python :: 3.10
Classifier: Programming Language :: Python :: 3.11
Classifier: Programming Language :: Python :: 3.12
Classifier: Programming Language :: Python :: 3.13
Classifier: License :: OSI Approved :: MIT License
Classifier: Operating System :: OS Independent
Classifier: Intended Audience :: Developers
Classifier: Topic :: Database
Classifier: Topic :: Scientific/Engineering :: Information Analysis
Classifier: Development Status :: 4 - Beta
Requires-Python: >=3.9
License-File: LICENSE.md
Requires-Dist: datasketch>=1.5.0
Requires-Dist: tqdm>=4.60.0
Requires-Dist: SQLAlchemy>=1.4.0
Requires-Dist: pydantic>=2.0.0
Requires-Dist: requests>=2.25.0
Requires-Dist: paramiko>=3.4.0
Provides-Extra: postgresql
Requires-Dist: psycopg2-binary>=2.9.0; extra == "postgresql"
Provides-Extra: mariadb
Requires-Dist: mariadb>=1.1.0; extra == "mariadb"
Provides-Extra: sqlserver
Requires-Dist: pyodbc>=4.0.0; extra == "sqlserver"
Provides-Extra: informix
Requires-Dist: pyodbc>=4.0.0; extra == "informix"
Requires-Dist: paramiko>=3.4.0; extra == "informix"
Provides-Extra: sqlite
Provides-Extra: all
Requires-Dist: psycopg2-binary>=2.9.0; extra == "all"
Requires-Dist: mariadb>=1.1.0; extra == "all"
Requires-Dist: pyodbc>=4.0.0; extra == "all"
Requires-Dist: paramiko>=3.4.0; extra == "all"
Provides-Extra: dev
Requires-Dist: pytest>=7.0.0; extra == "dev"
Requires-Dist: pytest-cov>=4.0.0; extra == "dev"
Requires-Dist: black>=22.0.0; extra == "dev"
Requires-Dist: flake8>=5.0.0; extra == "dev"
Requires-Dist: mypy>=1.0.0; extra == "dev"
Requires-Dist: pre-commit>=3.0.0; extra == "dev"
Requires-Dist: build>=1.0.0; extra == "dev"
Requires-Dist: twine>=4.0.0; extra == "dev"
Requires-Dist: psutil>=5.8.0; extra == "dev"
Requires-Dist: docker>=6.0.0; extra == "dev"
Provides-Extra: test-postgresql
Requires-Dist: pytest>=7.0.0; extra == "test-postgresql"
Requires-Dist: psycopg2-binary>=2.9.0; extra == "test-postgresql"
Provides-Extra: test-mariadb
Requires-Dist: pytest>=7.0.0; extra == "test-mariadb"
Requires-Dist: mariadb>=1.1.0; extra == "test-mariadb"
Provides-Extra: test-sqlserver
Requires-Dist: pytest>=7.0.0; extra == "test-sqlserver"
Requires-Dist: pyodbc>=4.0.0; extra == "test-sqlserver"
Provides-Extra: test-informix
Requires-Dist: pytest>=7.0.0; extra == "test-informix"
Requires-Dist: pyodbc>=4.0.0; extra == "test-informix"
Requires-Dist: paramiko>=3.4.0; extra == "test-informix"
Dynamic: license-file
